slap/core/semver/__init__.py
slap/core/semver/py.typed
slap/core/semver/specifier.py
slap/core/semver/utils.py
slap.core.semver-0.1.0dev1.dist-info/LICENSE
slap.core.semver-0.1.0dev1.dist-info/WHEEL
slap.core.semver-0.1.0dev1.dist-info/METADATA
slap.core.semver-0.1.0dev1.dist-info/RECORD
