Metadata-Version: 2.1
Name: slap.core.semver
Version: 0.1.0dev1
Summary: Provides a semver specifier to represent version constraints compatible with `packaging`.
License: MIT
Author: Niklas Rosenstein
Author-email: rosensteinniklas@gmail.com
Requires-Python: >=3.6,<4.0
Classifier: License :: OSI Approved :: MIT License
Classifier: Programming Language :: Python :: 3
Classifier: Programming Language :: Python :: 3.6
Classifier: Programming Language :: Python :: 3.7
Classifier: Programming Language :: Python :: 3.8
Classifier: Programming Language :: Python :: 3.9
Classifier: Programming Language :: Python :: 3.10
Requires-Dist: packaging (>=21.3,<22.0)
Project-URL: Bug Tracker, https://github.com/python-slap/slap.core.semver/issues
Project-URL: Repository, https://github.com/python-slap/slap.core.semver
